voicelab/__init__.py
voicelab/docs/.buildinfo
voicelab/docs/.doctrees/environment.pickle
voicelab/docs/.doctrees/index.doctree
voicelab/docs/.nojekyll
voicelab/docs/_images/LoadVoices.png
voicelab/docs/_images/output_window.png
voicelab/docs/_images/power_spectrum.png
voicelab/docs/_images/settings.png
voicelab/docs/_images/spectrogram.png
voicelab/docs/_sources/conf.py
voicelab/docs/_sources/favicon.ico
voicelab/docs/_sources/index.rst
voicelab/docs/_sources/index.rst.backup
voicelab/docs/_sources/index.rst.txt
voicelab/docs/_static/LoadVoices.png
voicelab/docs/_static/ajax-loader.gif
voicelab/docs/_static/alabaster.css
voicelab/docs/_static/basic.css
voicelab/docs/_static/comment-bright.png
voicelab/docs/_static/comment-close.png
voicelab/docs/_static/comment.png
voicelab/docs/_static/css/badge_only.css
voicelab/docs/_static/css/darker.css
voicelab/docs/_static/css/favicon.ico
voicelab/docs/_static/css/fonts/Roboto-Slab-Bold.woff
voicelab/docs/_static/css/fonts/Roboto-Slab-Bold.woff2
voicelab/docs/_static/css/fonts/Roboto-Slab-Regular.woff
voicelab/docs/_static/css/fonts/Roboto-Slab-Regular.woff2
voicelab/docs/_static/css/fonts/fontawesome-webfont.eot
voicelab/docs/_static/css/fonts/fontawesome-webfont.svg
voicelab/docs/_static/css/fonts/fontawesome-webfont.ttf
voicelab/docs/_static/css/fonts/fontawesome-webfont.woff
voicelab/docs/_static/css/fonts/fontawesome-webfont.woff2
voicelab/docs/_static/css/fonts/lato-bold-italic.woff
voicelab/docs/_static/css/fonts/lato-bold-italic.woff2
voicelab/docs/_static/css/fonts/lato-bold.woff
voicelab/docs/_static/css/fonts/lato-bold.woff2
voicelab/docs/_static/css/fonts/lato-normal-italic.woff
voicelab/docs/_static/css/fonts/lato-normal-italic.woff2
voicelab/docs/_static/css/fonts/lato-normal.woff
voicelab/docs/_static/css/fonts/lato-normal.woff2
voicelab/docs/_static/css/pdj.css
voicelab/docs/_static/css/theme.css
voicelab/docs/_static/custom.css
voicelab/docs/_static/doctools.js
voicelab/docs/_static/documentation_options.js
voicelab-2.0.0.dist-info/METADATA
voicelab-2.0.0.dist-info/WHEEL
voicelab-2.0.0.dist-info/entry_points.txt
voicelab-2.0.0.dist-info/RECORD
