Metadata-Version: 2.1
Name: voicelab
Version: 2.0.0
Summary: Automated Reproducible Voice Analysis
License: MIT
Author: David Feinberg
Author-email: feinberg@mcmaster.ca
Requires-Python: >=3.9,<=3.11.3
Classifier: License :: OSI Approved :: MIT License
Classifier: Programming Language :: Python :: 3
Classifier: Programming Language :: Python :: 3.9
Classifier: Programming Language :: Python :: 3.10
Classifier: Programming Language :: Python :: 3.11
Requires-Dist: PyQt5 (>=5.15.3)
Requires-Dist: QDarkStyle (==2.8.1)
Requires-Dist: librosa (==0.9.2)
Requires-Dist: numpy (>=1.22)
Requires-Dist: openpyxl (==3.0.6)
Requires-Dist: praat-parselmouth (>=0.4.1)
Requires-Dist: seaborn (==0.11.1)
